examples/__init__.py
examples/raster_and_shape_to_mask.py
examples/test_labelme2mask.py
examples/test_raster2png.py
examples/test_shp2labelme.py
raster2ML/__init__.py
raster2ML/labelme2mask.py
raster2ML/raster2png.py
raster2ML/shp2labelme.py
raster2ML-0.1.1.dist-info/METADATA
raster2ML-0.1.1.dist-info/WHEEL
raster2ML-0.1.1.dist-info/top_level.txt
raster2ML-0.1.1.dist-info/RECORD
